ACKNOWLEDGEMENTS
LICENSE
MANIFEST.in
README
dependencies.ini
run_tests.py
setup.cfg
setup.py
config/dpkg/changelog
config/dpkg/clean
config/dpkg/compat
config/dpkg/control
config/dpkg/copyright
config/dpkg/python-dtformats.install
config/dpkg/python3-dtformats.install
config/dpkg/rules
config/dpkg/source/format
config/travis/install.sh
config/travis/run_with_timeout.sh
config/travis/runtests.sh
data/avrf.yaml
data/core.yaml
data/cpio.yaml
data/guid.yaml
data/job.yaml
data/mdmp.yaml
dtformats/__init__.py
dtformats/asl.py
dtformats/asl.yaml
dtformats/chrome_cache.py
dtformats/chrome_cache.yaml
dtformats/cpio.py
dtformats/cpio.yaml
dtformats/cups_ipp.py
dtformats/cups_ipp.yaml
dtformats/data_format.py
dtformats/data_range.py
dtformats/emf.yaml
dtformats/errors.py
dtformats/gzipfile.py
dtformats/gzipfile.yaml
dtformats/job.py
dtformats/job.yaml
dtformats/jump_list.py
dtformats/jump_list.yaml
dtformats/output_writers.py
dtformats/py2to3.py
dtformats/rp_change_log.py
dtformats/rp_change_log.yaml
dtformats/rp_log.py
dtformats/rp_log.yaml
dtformats/safari_cookies.py
dtformats/safari_cookies.yaml
dtformats/tzif.py
dtformats/tzif.yaml
dtformats/utmp.py
dtformats/utmp.yaml
dtformats/wemf.py
dtformats/wmf.yaml
dtformats/wmi_repository.py
dtformats/wmi_repository.yaml
dtformats.egg-info/PKG-INFO
dtformats.egg-info/SOURCES.txt
dtformats.egg-info/dependency_links.txt
dtformats.egg-info/top_level.txt
scripts/asl.py
scripts/chrome_cache.py
scripts/cpio.py
scripts/cups_ipp.py
scripts/gzipfile.py
scripts/job.py
scripts/jump_list.py
scripts/rp_change_log.py
scripts/rp_log.py
scripts/safari_cookies.py
scripts/tzif.py
scripts/utmp.py
scripts/wemf.py
scripts/wmi_repository.py
test_data/1b4dd67f29cb1962.automaticDestinations-ms
test_data/5afe4de1b92fc382.customDestinations-ms
test_data/9d1f905ce5044aee.automaticDestinations-ms
test_data/Cookies.binarycookies
test_data/Memo.emf
test_data/change.log.1
test_data/cups_ipp_2.0
test_data/grid.wmf
test_data/rp.log
test_data/syslog.gz
test_data/utmp
test_data/wintask.job
test_data/chrome_cache/data_0
test_data/chrome_cache/data_1
test_data/chrome_cache/data_2
