Metadata-Version: 1.1
Name: dtformats
Version: 20180527
Summary: Data formats (dtformats)
Home-page: https://github.com/libyal/dtformats
Author: Joachim Metz
Author-email: joachim.metz@gmail.com
License: Apache License, Version 2.0
Platform: UNKNOWN
Classifier: Development Status :: 3 - Alpha
Classifier: Environment :: Console
Classifier: Operating System :: OS Independent
Classifier: Programming Language :: Python
